sd_parsers/__init__.py
sd_parsers/__main__.py
sd_parsers/_parser_manager.py
sd_parsers/exceptions.py
sd_parsers/py.typed
sd_parsers/data/__init__.py
sd_parsers/data/generators.py
sd_parsers/data/model.py
sd_parsers/data/prompt.py
sd_parsers/data/prompt_info.py
sd_parsers/data/sampler.py
sd_parsers/extractors/__init__.py
sd_parsers/extractors/_get_exif_value.py
sd_parsers/extractors/_jpeg_usercomment.py
sd_parsers/extractors/_png_image_info.py
sd_parsers/extractors/_png_image_text.py
sd_parsers/extractors/_png_stenographic_alpha.py
sd_parsers/parsers/__init__.py
sd_parsers/parsers/_automatic1111.py
sd_parsers/parsers/_comfyui.py
sd_parsers/parsers/_dummy_parser.py
sd_parsers/parsers/_fooocus.py
sd_parsers/parsers/_novelai.py
sd_parsers/parsers/_parser.py
sd_parsers/parsers/_invokeai/__init__.py
sd_parsers/parsers/_invokeai/_variant_dream.py
sd_parsers/parsers/_invokeai/_variant_invokeai_meta.py
sd_parsers/parsers/_invokeai/_variant_sd_metadata.py
sd_parsers/parsers/_invokeai/parser.py
sd_parsers-0.6.dist-info/licenses/LICENSE.txt
sd_parsers-0.6.dist-info/METADATA
sd_parsers-0.6.dist-info/WHEEL
sd_parsers-0.6.dist-info/top_level.txt
sd_parsers-0.6.dist-info/RECORD
