Metadata-Version: 2.4
Name: sd-parsers
Version: 0.6
Summary: a library to read metadata from images created by Stable Diffusion
Author: d3x-at
License: MIT License
Project-URL: repository, https://github.com/d3x-at/sd-parsers
Classifier: License :: OSI Approved :: MIT License
Classifier: Programming Language :: Python :: 3 :: Only
Classifier: Programming Language :: Python :: 3.9
Classifier: Programming Language :: Python :: 3.10
Classifier: Programming Language :: Python :: 3.11
Classifier: Programming Language :: Python :: 3.12
Classifier: Programming Language :: Python :: 3.13
Classifier: Topic :: Multimedia :: Graphics
Classifier: Topic :: Scientific/Engineering :: Image Processing
Classifier: Topic :: Software Development :: Libraries :: Python Modules
Requires-Python: >=3.9
License-File: LICENSE.txt
Requires-Dist: pillow>=10.4.0
Dynamic: license-file
